echolog/__init__.py
echolog/demo.py
echolog-0.0.5.dist-info/METADATA
echolog-0.0.5.dist-info/WHEEL
echolog-0.0.5.dist-info/licenses/LICENSE
echolog-0.0.5.dist-info/RECORD
