Metadata-Version: 2.1
Name: echolog
Version: 0.0.5
Summary: A logging package that adds an echo() function to return both the input expression/variable and its results. Also sets up nicely-formatted logging.
Project-URL: Homepage, https://github.com/nerdpersonthing/echolog
Author: nerdpersonthing
License-File: LICENSE
Classifier: License :: OSI Approved :: MIT License
Classifier: Operating System :: OS Independent
Classifier: Programming Language :: Python :: 3
Requires-Python: >=3.7
Requires-Dist: ansicon; os_name == 'nt'
Requires-Dist: datetime
Requires-Dist: dotmap
